reposcraper/__init__.py
reposcraper/lib/main.py
reposcraper/lib/utils.py
reposcraper/swagger/swagger_config.json
repo_scraper-0.1.2.dist-info/LICENSE
repo_scraper-0.1.2.dist-info/METADATA
repo_scraper-0.1.2.dist-info/WHEEL
repo_scraper-0.1.2.dist-info/top_level.txt
repo_scraper-0.1.2.dist-info/RECORD
