Metadata-Version: 2.1
Name: repo-scraper
Version: 0.1.2
Summary: Restful API for the codesurvey Python library.
Author-email: Elliot Simpson <elliot@p-s.co.nz>
License: GNU AGPL
Project-URL: Homepage, https://github.com/ByteCampNZ/repo-scraper
Keywords: repository,scraper,git
Classifier: Intended Audience :: Developers
Classifier: Programming Language :: Python :: 3
Requires-Python: >=3.7
License-File: LICENSE
Requires-Dist: codesurvey ==0.1.3
Requires-Dist: flasgger ==0.9.7.1
Requires-Dist: Flask ==3.0.0
Requires-Dist: Flask-RESTful ==0.3.10
Requires-Dist: shortuuid ==1.0.11
